{
    "session_id": 173,
    "title": "Critical Challenges and Interfaces to Autonomous Systems",
    "views": 20,
    "total_favs": 21,
    "fav_count": 21,
    "unfav_count": 0,
    "session_notes": 0,
    "space": "Dilemmas in connected spaces",
    "pathway": "",
    "language": "",
    "etherpad": "https://public.etherpad-mozilla.org/p/mozfest-2016-critical-challenges-and-interfaces-to",
    "notes": "Welcome to Etherpad!\n\nThis pad text is synchronized as you type, so that everyone viewing this page sees the same text. This allows you to collaborate seamlessly on documents!\n\nGet involved with Etherpad at http://etherpad.org\n\n",
    "id": 173,
    "url": "https://public.etherpad-mozilla.org/p/mozfest-2016-critical-challenges-and-interfaces-to/export/txt",
    "empty": true,
    "character_count": 0,
    "term_occurrence": {
        "open": 0,
        "libre": 0,
        "innovation": 0,
        "inclusion": 0,
        "privacy": 0,
        "science": 0
    }
}